Workbook

Sheet Executive Dashboard
B2: FLIPKART / SALES INTELLIGENCE
B4: EXECUTIVE OVERVIEW • FY 2024–2025 • 1,000 TRANSACTIONS
B6: REVENUE / PROFITABILITY / PRODUCT MIX / CHANNEL PERFORMANCE
B8: GROSS SALES | C8: GROSS SALES | D8: GROSS SALES | F8: NET SALES | G8: NET SALES | H8: NET SALES | J8: TOTAL PROFIT | K8: TOTAL PROFIT | L8: TOTAL PROFIT | M8: PROFIT MARGIN | N8: PROFIT MARGIN | O8: PROFIT MARGIN
B9: =SUM('Sales Data'!K2:K1001) -> 18694940 | F9: =SUM('Sales Data'!N2:N1001) -> 17254543 | J9: =SUM('Sales Data'!P2:P1001) -> 5374171.2 | M9: =IFERROR(J9/F9,0) -> 0.31146412
B14: 01 | YEAR-ON-YEAR SALES | J14: 02 | CATEGORY PERFORMANCE
B30: 03 | REGIONAL CONTRIBUTION | J30: 04 | SALES CHANNELS
B45: EXECUTIVE TAKEAWAYS
B46: 2025 net sales declined by 6.5% compared with 2024. Clothing leads category revenue at ₹4.83M, while East is the highest-performing region at ₹4.52M. Online is the strongest sales channel at ₹8.83M, highlighting the importance of digital sales.

Sheet Analysis
A1: SALES PERFORMANCE | SOURCE-BASED SUMMARIES
A3: Year | B3: Net Sales | C3: Gross Sales | D3: Profit | E3: Units Sold | G3: Category | H3: Net Sales | I3: Gross Sales | J3: Profit
A4: 2024 | B4: =SUMIF('Sales Data'!$C$2:$C$1001,$A4,'Sales Data'!$N$2:$N$1001) -> 8918201.8 | C4: =SUMIF('Sales Data'!$C$2:$C$1001,$A4,'Sales Data'!$K$2:$K$1001) -> 9719294.3 | D4: =SUMIF('Sales Data'!$C$2:$C$1001,$A4,'Sales Data'!$P$2:$P$1001) -> 2688646.2 | E4: =SUMIF('Sales Data'!$C$2:$C$1001,$A4,'Sales Data'!$H$2:$H$1001) -> 13002 | G4: Clothing | H4: =SUMIF('Sales Data'!$F$2:$F$1001,$G4,'Sales Data'!$N$2:$N$1001) -> 4826702.3 | I4: =SUMIF('Sales Data'!$F$2:$F$1001,$G4,'Sales Data'!$K$2:$K$1001) -> 5174035.9 | J4: =SUMIF('Sales Data'!$F$2:$F$1001,$G4,'Sales Data'!$P$2:$P$1001) -> 2362898.2
A5: 2025 | B5: =SUMIF('Sales Data'!$C$2:$C$1001,$A5,'Sales Data'!$N$2:$N$1001) -> 8336341.6 | C5: =SUMIF('Sales Data'!$C$2:$C$1001,$A5,'Sales Data'!$K$2:$K$1001) -> 8975646 | D5: =SUMIF('Sales Data'!$C$2:$C$1001,$A5,'Sales Data'!$P$2:$P$1001) -> 2685525 | E5: =SUMIF('Sales Data'!$C$2:$C$1001,$A5,'Sales Data'!$H$2:$H$1001) -> 11886 | G5: Food | H5: =SUMIF('Sales Data'!$F$2:$F$1001,$G5,'Sales Data'!$N$2:$N$1001) -> 4502965.5 | I5: =SUMIF('Sales Data'!$F$2:$F$1001,$G5,'Sales Data'!$K$2:$K$1001) -> 4884800.9 | J5: =SUMIF('Sales Data'!$F$2:$F$1001,$G5,'Sales Data'!$P$2:$P$1001) -> 1057051.3
G6: Electronics | H6: =SUMIF('Sales Data'!$F$2:$F$1001,$G6,'Sales Data'!$N$2:$N$1001) -> 4029938.9 | I6: =SUMIF('Sales Data'!$F$2:$F$1001,$G6,'Sales Data'!$K$2:$K$1001) -> 4425035.7 | J6: =SUMIF('Sales Data'!$F$2:$F$1001,$G6,'Sales Data'!$P$2:$P$1001) -> 604357.25
G7: Furniture | H7: =SUMIF('Sales Data'!$F$2:$F$1001,$G7,'Sales Data'!$N$2:$N$1001) -> 3894936.7 | I7: =SUMIF('Sales Data'!$F$2:$F$1001,$G7,'Sales Data'!$K$2:$K$1001) -> 4211067.8 | J7: =SUMIF('Sales Data'!$F$2:$F$1001,$G7,'Sales Data'!$P$2:$P$1001) -> 1349864.4
A11: Region | B11: Net Sales | C11: Gross Sales | D11: Profit
A12: East | B12: =SUMIF('Sales Data'!$D$2:$D$1001,$A12,'Sales Data'!$N$2:$N$1001) -> 4521974.3 | C12: =SUMIF('Sales Data'!$D$2:$D$1001,$A12,'Sales Data'!$K$2:$K$1001) -> 4934216.9 | D12: =SUMIF('Sales Data'!$D$2:$D$1001,$A12,'Sales Data'!$P$2:$P$1001) -> 1407925.6 | G12: Product | H12: Net Sales | I12: Gross Sales
A13: North | B13: =SUMIF('Sales Data'!$D$2:$D$1001,$A13,'Sales Data'!$N$2:$N$1001) -> 4438747.8 | C13: =SUMIF('Sales Data'!$D$2:$D$1001,$A13,'Sales Data'!$K$2:$K$1001) -> 4744199.9 | D13: =SUMIF('Sales Data'!$D$2:$D$1001,$A13,'Sales Data'!$P$2:$P$1001) -> 1416999.4 | G13: Chair | H13: =SUMIF('Sales Data'!$G$2:$G$1001,$G13,'Sales Data'!$N$2:$N$1001) -> 1738752.3 | I13: =SUMIF('Sales Data'!$G$2:$G$1001,$G13,'Sales Data'!$K$2:$K$1001) -> 1904930.6
A14: South | B14: =SUMIF('Sales Data'!$D$2:$D$1001,$A14,'Sales Data'!$N$2:$N$1001) -> 4317442.8 | C14: =SUMIF('Sales Data'!$D$2:$D$1001,$A14,'Sales Data'!$K$2:$K$1001) -> 4718362.4 | D14: =SUMIF('Sales Data'!$D$2:$D$1001,$A14,'Sales Data'!$P$2:$P$1001) -> 1287223 | G14: Shirt | H14: =SUMIF('Sales Data'!$G$2:$G$1001,$G14,'Sales Data'!$N$2:$N$1001) -> 1705189.7 | I14: =SUMIF('Sales Data'!$G$2:$G$1001,$G14,'Sales Data'!$K$2:$K$1001) -> 1808519.8
A15: West | B15: =SUMIF('Sales Data'!$D$2:$D$1001,$A15,'Sales Data'!$N$2:$N$1001) -> 3976378.5 | C15: =SUMIF('Sales Data'!$D$2:$D$1001,$A15,'Sales Data'!$K$2:$K$1001) -> 4298161.2 | D15: =SUMIF('Sales Data'!$D$2:$D$1001,$A15,'Sales Data'!$P$2:$P$1001) -> 1262023.2 | G15: Beverage | H15: =SUMIF('Sales Data'!$G$2:$G$1001,$G15,'Sales Data'!$N$2:$N$1001) -> 1678656.5 | I15: =SUMIF('Sales Data'!$G$2:$G$1001,$G15,'Sales Data'!$K$2:$K$1001) -> 1828711.6
G16: Jeans | H16: =SUMIF('Sales Data'!$G$2:$G$1001,$G16,'Sales Data'!$N$2:$N$1001) -> 1620628.4 | I16: =SUMIF('Sales Data'!$G$2:$G$1001,$G16,'Sales Data'!$K$2:$K$1001) -> 1741403.2
G17: Cereal | H17: =SUMIF('Sales Data'!$G$2:$G$1001,$G17,'Sales Data'!$N$2:$N$1001) -> 1602044.2 | I17: =SUMIF('Sales Data'!$G$2:$G$1001,$G17,'Sales Data'!$K$2:$K$1001) -> 1729543.9
G18: Jacket | H18: =SUMIF('Sales Data'!$G$2:$G$1001,$G18,'Sales Data'!$N$2:$N$1001) -> 1500884.2 | I18: =SUMIF('Sales Data'!$G$2:$G$1001,$G18,'Sales Data'!$K$2:$K$1001) -> 1624113
G19: Phone | H19: =SUMIF('Sales Data'!$G$2:$G$1001,$G19,'Sales Data'!$N$2:$N$1001) -> 1493963.2 | I19: =SUMIF('Sales Data'!$G$2:$G$1001,$G19,'Sales Data'!$K$2:$K$1001) -> 1636978.4
G20: Laptop | H20: =SUMIF('Sales Data'!$G$2:$G$1001,$G20,'Sales Data'!$N$2:$N$1001) -> 1317616.1 | I20: =SUMIF('Sales Data'!$G$2:$G$1001,$G20,'Sales Data'!$K$2:$K$1001) -> 1438983.4
A21: Payment Method | B21: Net Sales | C21: Units Sold | G21: Cabinet | H21: =SUMIF('Sales Data'!$G$2:$G$1001,$G21,'Sales Data'!$N$2:$N$1001) -> 1266365.8 | I21: =SUMIF('Sales Data'!$G$2:$G$1001,$G21,'Sales Data'!$K$2:$K$1001) -> 1331312
A22: Credit Card | B22: =SUMIF('Sales Data'!$S$2:$S$1001,$A22,'Sales Data'!$N$2:$N$1001) -> 8382650.5 | C22: =SUMIF('Sales Data'!$S$2:$S$1001,$A22,'Sales Data'!$H$2:$H$1001) -> 11869 | G22: Snacks | H22: =SUMIF('Sales Data'!$G$2:$G$1001,$G22,'Sales Data'!$N$2:$N$1001) -> 1222264.8 | I22: =SUMIF('Sales Data'!$G$2:$G$1001,$G22,'Sales Data'!$K$2:$K$1001) -> 1326545.3
A23: PayPal | B23: =SUMIF('Sales Data'!$S$2:$S$1001,$A23,'Sales Data'!$N$2:$N$1001) -> 4377132.7 | C23: =SUMIF('Sales Data'!$S$2:$S$1001,$A23,'Sales Data'!$H$2:$H$1001) -> 6433 | G23: Tablet | H23: =SUMIF('Sales Data'!$G$2:$G$1001,$G23,'Sales Data'!$N$2:$N$1001) -> 1218359.7 | I23: =SUMIF('Sales Data'!$G$2:$G$1001,$G23,'Sales Data'!$K$2:$K$1001) -> 1349074
A24: Cash | B24: =SUMIF('Sales Data'!$S$2:$S$1001,$A24,'Sales Data'!$N$2:$N$1001) -> 2356805.8 | C24: =SUMIF('Sales Data'!$S$2:$S$1001,$A24,'Sales Data'!$H$2:$H$1001) -> 3400 | G24: Desk | H24: =SUMIF('Sales Data'!$G$2:$G$1001,$G24,'Sales Data'!$N$2:$N$1001) -> 889818.62 | I24: =SUMIF('Sales Data'!$G$2:$G$1001,$G24,'Sales Data'!$K$2:$K$1001) -> 974825.18
A25: Debit Card | B25: =SUMIF('Sales Data'!$S$2:$S$1001,$A25,'Sales Data'!$N$2:$N$1001) -> 2137954.5 | C25: =SUMIF('Sales Data'!$S$2:$S$1001,$A25,'Sales Data'!$H$2:$H$1001) -> 3186
G32: Sales Channel | H32: Net Sales | I32: Units Sold
G33: Online | H33: =SUMIF('Sales Data'!$R$2:$R$1001,$G33,'Sales Data'!$N$2:$N$1001) -> 8831861.2 | I33: =SUMIF('Sales Data'!$R$2:$R$1001,$G33,'Sales Data'!$H$2:$H$1001) -> 12568
G34: In-Store | H34: =SUMIF('Sales Data'!$R$2:$R$1001,$G34,'Sales Data'!$N$2:$N$1001) -> 5641106 | I34: =SUMIF('Sales Data'!$R$2:$R$1001,$G34,'Sales Data'!$H$2:$H$1001) -> 8352
G35: Mobile App | H35: =SUMIF('Sales Data'!$R$2:$R$1001,$G35,'Sales Data'!$N$2:$N$1001) -> 2781576.3 | I35: =SUMIF('Sales Data'!$R$2:$R$1001,$G35,'Sales Data'!$H$2:$H$1001) -> 3968
A41: SOURCE: Original uploaded FLIPKART PROJECT workbook, Innovative_Sales_Data worksheet.
A42: Figures are based on all 1,000 original records; dashboard KPIs link to Sales Data.
A43: The original workbook with PivotTables and original dashboard remains unchanged.

Sheet Sales Data
A1: Order_ID | B1: Date | C1: Year | D1: Region | E1: Customer Segment | F1: Category | G1: Product | H1: Units Sold | I1: Unit Price | J1: Unit Cost | K1: Gross Sales | L1: Discount% | M1: Discount Amt | N1: Net Sales | O1: Total Cost | P1: Profit | Q1: Profit Margin % | R1: Sales_Channel | S1: Payment_Method | T1: Ratings
A2: ORD00001 | B2: 45293 | C2: 2024 | D2: West | E2: Consumer | F2: Clothing | G2: Jeans | H2: 33 | I2: 1362.09 | J2: 689.71 | K2: =H2*I2 -> 44948.97 | L2: 0 | M2: =K2*L2 -> 0 | N2: =K2-M2 -> 44948.97 | O2: =H2*J2 -> 22760.43 | P2: =N2-O2 -> 22188.54 | Q2: =IFERROR(P2/N2*100,0) -> 49.363845 | R2: Online | S2: PayPal | T2: 3.6
A3: ORD00002 | B3: 45293 | C3: 2024 | D3: North | E3: Corporate | F3: Clothing | G3: Jacket | H3: 43 | I3: 984.5 | J3: 356.71 | K3: =H3*I3 -> 42333.5 | L3: 0.05 | M3: =K3*L3 -> 2116.675 | N3: =K3-M3 -> 40216.825 | O3: =H3*J3 -> 15338.53 | P3: =N3-O3 -> 24878.295 | Q3: =IFERROR(P3/N3*100,0) -> 61.860415 | R3: Online | S3: Cash | T3: 3.8
A4: ORD00003 | B4: 45293 | C4: 2024 | D4: South | E4: Corporate | F4: Electronics | G4: Tablet | H4: 43 | I4: 1328.52 | J4: 983.37 | K4: =H4*I4 -> 57126.36 | L4: 0.2 | M4: =K4*L4 -> 11425.272 | N4: =K4-M4 -> 45701.088 | O4: =H4*J4 -> 42284.91 | P4: =N4-O4 -> 3416.178 | Q4: =IFERROR(P4/N4*100,0) -> 7.4750474 | R4: Mobile App | S4: Credit Card | T4: 4.5
A5: ORD00004 | B5: 45294 | C5: 2024 | D5: West | E5: Consumer | F5: Clothing | G5: Shirt | H5: 18 | I5: 1407.57 | J5: 633.88 | K5: =H5*I5 -> 25336.26 | L5: 0.1 | M5: =K5*L5 -> 2533.626 | N5: =K5-M5 -> 22802.634 | O5: =H5*J5 -> 11409.84 | P5: =N5-O5 -> 11392.794 | Q5: =IFERROR(P5/N5*100,0) -> 49.962623 | R5: Online | S5: PayPal | T5: 3.3
A6: ORD00005 | B6: 45295 | C6: 2024 | D6: North | E6: Consumer | F6: Food | G6: Snacks | H6: 35 | I6: 280.2 | J6: 215.42 | K6: =H6*I6 -> 9807 | L6: 0.15 | M6: =K6*L6 -> 1471.05 | N6: =K6-M6 -> 8335.95 | O6: =H6*J6 -> 7539.7 | P6: =N6-O6 -> 796.25 | Q6: =IFERROR(P6/N6*100,0) -> 9.5520007 | R6: Online | S6: PayPal | T6: 3.3
A7: ORD00006 | B7: 45295 | C7: 2024 | D7: South | E7: Consumer | F7: Food | G7: Snacks | H7: 9 | I7: 596.08 | J7: 458.27 | K7: =H7*I7 -> 5364.72 | L7: 0.1 | M7: =K7*L7 -> 536.472 | N7: =K7-M7 -> 4828.248 | O7: =H7*J7 -> 4124.43 | P7: =N7-O7 -> 703.818 | Q7: =IFERROR(P7/N7*100,0) -> 14.577089 | R7: In-Store | S7: Cash | T7: 3.9
A8: ORD00007 | B8: 45296 | C8: 2024 | D8: East | E8: Consumer | F8: Clothing | G8: Shirt | H8: 14 | I8: 737.11 | J8: 431.56 | K8: =H8*I8 -> 10319.54 | L8: 0.1 | M8: =K8*L8 -> 1031.954 | N8: =K8-M8 -> 9287.586 | O8: =H8*J8 -> 6041.84 | P8: =N8-O8 -> 3245.746 | Q8: =IFERROR(P8/N8*100,0) -> 34.947143 | R8: Online | S8: Debit Card | T8: 4.5
A9: ORD00008 | B9: 45297 | C9: 2024 | D9: East | E9: Consumer | F9: Clothing | G9: Jacket | H9: 48 | I9: 788.47 | J9: 302.34 | K9: =H9*I9 -> 37846.56 | L9: 0.15 | M9: =K9*L9 -> 5676.984 | N9: =K9-M9 -> 32169.576 | O9: =H9*J9 -> 14512.32 | P9: =N9-O9 -> 17657.256 | Q9: =IFERROR(P9/N9*100,0) -> 54.888059 | R9: In-Store | S9: Credit Card | T9: 4
A10: ORD00009 | B10: 45297 | C10: 2024 | D10: South | E10: Corporate | F10: Furniture | G10: Cabinet | H10: 29 | I10: 639.2 | J10: 370.59 | K10: =H10*I10 -> 18536.8 | L10: 0 | M10: =K10*L10 -> 0 | N10: =K10-M10 -> 18536.8 | O10: =H10*J10 -> 10747.11 | P10: =N10-O10 -> 7789.69 | Q10: =IFERROR(P10/N10*100,0) -> 42.022841 | R10: Online | S10: PayPal | T10: 4
A11: ORD00010 | B11: 45298 | C11: 2024 | D11: East | E11: Consumer | F11: Furniture | G11: Desk | H11: 13 | I11: 152.06 | J11: 84.91 | K11: =H11*I11 -> 1976.78 | L11: 0.05 | M11: =K11*L11 -> 98.839 | N11: =K11-M11 -> 1877.941 | O11: =H11*J11 -> 1103.83 | P11: =N11-O11 -> 774.111 | Q11: =IFERROR(P11/N11*100,0) -> 41.221263 | R11: Online | S11: Credit Card | T11: 4
A12: ORD00011 | B12: 45299 | C12: 2024 | D12: North | E12: Consumer | F12: Clothing | G12: Shirt | H12: 47 | I12: 1138.45 | J12: 677.21 | K12: =H12*I12 -> 53507.15 | L12: 0 | M12: =K12*L12 -> 0 | N12: =K12-M12 -> 53507.15 | O12: =H12*J12 -> 31828.87 | P12: =N12-O12 -> 21678.28 | Q12: =IFERROR(P12/N12*100,0) -> 40.514735 | R12: Online | S12: PayPal | T12: 3.5
A13: ORD00012 | B13: 45299 | C13: 2024 | D13: North | E13: Consumer | F13: Furniture | G13: Chair | H13: 5 | I13: 558.27 | J13: 282.49 | K13: =H13*I13 -> 2791.35 | L13: 0.25 | M13: =K13*L13 -> 697.8375 | N13: =K13-M13 -> 2093.5125 | O13: =H13*J13 -> 1412.45 | P13: =N13-O13 -> 681.0625 | Q13: =IFERROR(P13/N13*100,0) -> 32.532048 | R13: Online | S13: Credit Card | T13: 3.2
... A1001: ORD01000 | B1001: 46022 | C1001: 2025 | D1001: West | E1001: Consumer | F1001: Furniture | G1001: Cabinet | H1001: 10 | I1001: 251.17 | J1001: 153.41 | K1001: =H1001*I1001 -> 2511.7 | L1001: 0 | M1001: =K1001*L1001 -> 0 | N1001: =K1001-M1001 -> 2511.7 | O1001: =H1001*J1001 -> 1534.1 | P1001: =N1001-O1001 -> 977.6 | Q1001: =IFERROR(P1001/N1001*100,0) -> 38.921846 | R1001: Mobile App | S1001: Credit Card | T1001: 4.7

Sheet Formula Guide
A1: FLIPKART | FORMULA REFERENCE
A2: How to edit | B2: Edit Units Sold, Unit Price, Unit Cost or Discount% in Sales Data.
A3: What updates | B3: Sales Data calculated columns, Analysis tables and dashboard KPIs.
A4: Metric | B4: Formula pattern | C4: Source
A5: Gross Sales | B5: =Units Sold * Unit Price -> #NAME? | C5: Sales Data!K
A6: Discount Amount | B6: =Gross Sales * Discount% -> #NAME? | C6: Sales Data!M
A7: Net Sales | B7: #NAME? | C7: Sales Data!N
A8: Total Cost | B8: =Units Sold * Unit Cost -> #NAME? | C8: Sales Data!O
A9: Profit | B9: #NAME? | C9: Sales Data!P
A10: Profit Margin | B10: =Profit / Net Sales -> #NAME? | C10: Executive Dashboard!M9
A11: Yearly Sales | B11: =SUMIF(Year, selected Year, Net Sales) -> #NAME? | C11: Analysis!B4:B5
A12: Product Revenue | B12: =SUMIF(Product, selected Product, Net Sales) -> #NAME? | C12: Analysis!H13:H24
A13: NOTE | B13: Avoid changing formula cells in Sales Data columns K, M, N, O, P, Q.
